pysparkai/__init__.py
pysparkai/api_utils.py
pysparkai/auth_websocket_client.py
pysparkai/error_codes.py
pysparkai/pysparkai.py
xunfeispark-1.0.dist-info/LICENSE
xunfeispark-1.0.dist-info/METADATA
xunfeispark-1.0.dist-info/WHEEL
xunfeispark-1.0.dist-info/top_level.txt
xunfeispark-1.0.dist-info/RECORD
