Metadata-Version: 2.1
Name: xunfeispark
Version: 1.0
Summary: xunfeispark is a Python library for building AI applications.
Author-email: Shibo Li <shadow.li981@gmail.com>
License: MIT License
License-File: LICENSE
Requires-Dist: websocket-client
